[
    {
        "coordinates": [-71.0566478,42.3605884],
        "numspots": 1
    },
    {
        "coordinates": [-71.0529804, 42.3597105],
        "numspots": 1
    },
    {
        "coordinates": [-71.0530764, 42.358866],
        "numspots": 1
    },
    {
        "coordinates": [-71.0609191, 42.3621599],
        "numspots": 1
    },
    {
        "coordinates": [-71.0607594, 42.362289],
        "numspots": 1
    },
    {
        "coordinates": [-71.0605307, 42.3614474],
        "numspots": 1
    },
    {
        "coordinates": [-71.061605, 42.3587902],
        "numspots": 1
    },
    {
        "coordinates": [-71.0628802, 42.3590545],
        "numspots": 1
    },
    {
        "coordinates": [-71.0628288, 42.3590336],
        "numspots": 1
    },
    {
        "coordinates": [-71.062739, 42.3590456],
        "numspots": 1
    },
    {
        "coordinates": [-71.0722702, 42.2999349],
        "numspots": 1
    },
    {
        "coordinates": [-71.065081, 42.3604596],
        "numspots": 1
    },
    {
        "coordinates": [-71.0652568, 42.360917],
        "numspots": 1
    },
    {
        "coordinates": [-71.0653017, 42.3595269],
        "numspots": 1
    },
    {
        "coordinates": [-71.0645667, 42.3585008],
        "numspots": 1
    },
    {
        "coordinates": [-71.063973, 42.3594206],
        "numspots": 1
    },
    {
        "coordinates": [-71.1194061, 42.3599005],
        "numspots": 1
    },
    {
        "coordinates": [-71.0635527, 42.3620373],
        "numspots": 1
    },
    {
        "coordinates": [-71.063972, 42.3644379],
        "numspots": 1
    },
    {
        "coordinates": [-71.0625429, 42.3639065],
        "numspots": 1
    },
    {
        "coordinates": [-71.0621671, 42.3639688],
        "numspots": 1
    },
    {
        "coordinates": [-71.0603951, 42.3642348],
        "numspots": 1
    },
    {
        "coordinates": [-71.0594548, 42.3634469],
        "numspots": 1
    },
    {
        "coordinates": [-71.0606693, 42.3804097],
        "numspots": 1
    },
    {
        "coordinates": [-71.0572881, 42.3584392],
        "numspots": 1
    },
    {
        "coordinates": [-71.0568698, 42.3576883],
        "numspots": 1
    },
    {
        "coordinates": [-71.0584263, 42.3553195],
        "numspots": 1
    },
    {
        "coordinates": [-71.0580338, 42.3557565],
        "numspots": 1
    },
    {
        "coordinates": [-71.0540513, 42.3560286],
        "numspots": 1
    },
    {
        "coordinates": [-71.059575, 42.357281],
        "numspots": 1
    },
    {
        "coordinates": [-71.0534021, 42.3650128],
        "numspots": 1
    },
    {
        "coordinates": [-71.0533043, 42.3649048],
        "numspots": 1
    },
    {
        "coordinates": [-71.0527874, 42.3668374],
        "numspots": 1
    },
    {
        "coordinates": [-71.0526204, 42.3667707],
        "numspots": 1
    },
    {
        "coordinates": [-71.0528514, 42.3619877],
        "numspots": 1
    },
    {
        "coordinates": [-71.0516395, 42.3623309],
        "numspots": 1
    },
    {
        "coordinates": [-71.0518589, 42.3630802],
        "numspots": 1
    },
    {
        "coordinates": [-71.050973, 42.3660619],
        "numspots": 1
    },
    {
        "coordinates": [-71.0513005, 42.3661621],
        "numspots": 1
    },
    {
        "coordinates": [-71.0521156, 42.3667785],
        "numspots": 1
    },
    {
        "coordinates": [-71.0534823, 42.3676835],
        "numspots": 1
    },
    {
        "coordinates": [-71.0561109, 42.3682843],
        "numspots": 1
    },
    {
        "coordinates": [-71.053588, 42.366843],
        "numspots": 1
    },
    {
        "coordinates": [-71.054198, 42.36712],
        "numspots": 1
    },
    {
        "coordinates": [-71.054511, 42.36726],
        "numspots": 1
    },
    {
        "coordinates": [-71.0546981, 42.3672465],
        "numspots": 1
    },
    {
        "coordinates": [-71.052565, 42.366389],
        "numspots": 1
    },
    {
        "coordinates": [-71.0525357, 42.366245],
        "numspots": 1
    },
    {
        "coordinates": [-71.0523245, 42.3662128],
        "numspots": 1
    },
    {
        "coordinates": [-71.0532428, 42.3634196],
        "numspots": 1
    },
    {
        "coordinates": [-71.0520096, 42.3637823],
        "numspots": 1
    }
]